[{"name":"sql.active_record","payload":{"sql":"SELECT \"stories\".* FROM \"stories\"  WHERE \"stories\".\"user_id\" = 1","name":"Story Load","connection_id":70279344316700,"binds":[]},"time":"2013-11-11T21:33:49-05:00","transaction_id":"97f1e656671de99c62f3","end":"2013-11-11T21:33:49-05:00","duration":0.5109999999999999},{"name":"process_action.action_controller","payload":{"controller":"StoriesController","action":"index","params":{"action":"index","controller":"stories","user_id":"1"},"format":"json","method":"GET","path":"/users/1/stories","status":200,"view_runtime":0.9630000000000001,"db_runtime":0.5109999999999999},"time":"2013-11-11T21:33:49-05:00","transaction_id":"fd672790d99ff61865ab","end":"2013-11-11T21:33:49-05:00","duration":1.727}]